{
  "title": "A Research Note on Unconditional Cash Transfers and Fertility in the United States: New Causal Evidence",
  "abstract": "As cash transfer policies have gained traction in recent years, interest in how financial resources could impact fertility has also grown. Increasing an individ ual's purchasing power with additional economic resources, such as those provided in unconditional cash transfers, might better enable parents to meet their fertility and reproductive goals, whether those goals are to become pregnant and give birth or to avoid or terminate pregnancies. In this research note, we provide new experimental evidence of the causal impact of a monthly unconditional cash transfer on fertility related outcomes for U.S. families with at least one young child and low incomes. We find trends of increased pregnancy after three years but no corresponding impacts on births, miscarriages, or terminations. Our findings might indicate that modest cash transfers to mothers with low incomes in the United States are unlikely to have sub stantial impacts on fertility.",
  "authors": [
    {
      "raw": "Costanzo, Molly A.",
      "family": "Costanzo",
      "given": "Molly A."
    },
    {
      "raw": "Magnuson, Katherine A.",
      "family": "Magnuson",
      "given": "Katherine A."
    },
    {
      "raw": "Duncan, Greg J.",
      "family": "Duncan",
      "given": "Greg J."
    },
    {
      "raw": "Fox, Nathan",
      "family": "Fox",
      "given": "Nathan"
    },
    {
      "raw": "Gennetian, Lisa A.",
      "family": "Gennetian",
      "given": "Lisa A."
    },
    {
      "raw": "Halpern-Meekin, Sarah",
      "family": "Halpern-Meekin",
      "given": "Sarah"
    },
    {
      "raw": "Noble, Kimberly G.",
      "family": "Noble",
      "given": "Kimberly G."
    },
    {
      "raw": "Yoshikawa, Hirokazu",
      "family": "Yoshikawa",
      "given": "Hirokazu"
    }
  ],
  "authors_text": "Costanzo, Molly A.; Magnuson, Katherine A.; Duncan, Greg J.; Fox, Nathan; Gennetian, Lisa A.; Halpern-Meekin, Sarah; Noble, Kimberly G.; Yoshikawa, Hirokazu",
  "journal": "Demography",
  "journal_slug": "Demography",
  "year": 2025,
  "doi": "10.1215/00703370-11872728",
  "doi_url": "https://doi.org/10.1215/00703370-11872728",
  "share_url": "https://huwenbo-lab.github.io/publication/#doi/10.1215%2F00703370-11872728",
  "api_url": "https://huwenbo-lab.github.io/publication/api/articles/10.1215/00703370-11872728.json",
  "lit_db": {
    "overview": "https://raw.githubusercontent.com/huwenbo-lab/publication/main/lit_db/overview.md",
    "journal_titles": "https://raw.githubusercontent.com/huwenbo-lab/publication/main/lit_db/titles/by_journal/Demography.md",
    "journal_abstracts": "https://raw.githubusercontent.com/huwenbo-lab/publication/main/lit_db/abstracts/2020_2026/Demography.md"
  }
}
