{
  "title": "Measuring pregnancy planning",
  "abstract": "We evaluated the psychometric properties of the London Measure of Unplanned Pregnancy among Indian women using classical methods and Item Response Modeling. The scale exhibited good internal consistency and internal structure, with overall scores correlating well with each item's response categories. Items performed similarly for pregnant and non-pregnant women, and scores decreased with increasing parity, providing evidence for validity. Analyses also detected limitations, including infrequent selection of middle response categories and some evidence of differential item functioning by parity. We conclude that the LMUP represents an improvement over existing measures but recommend steps for enhancing scale performance for this cultural context.",
  "authors": [
    {
      "raw": "Rocca, Corinne",
      "family": "Rocca",
      "given": "Corinne"
    },
    {
      "raw": "Krishnan, Suneeta",
      "family": "Krishnan",
      "given": "Suneeta"
    },
    {
      "raw": "Barrett, Geraldine",
      "family": "Barrett",
      "given": "Geraldine"
    },
    {
      "raw": "Wilson, Mark",
      "family": "Wilson",
      "given": "Mark"
    }
  ],
  "authors_text": "Rocca, Corinne; Krishnan, Suneeta; Barrett, Geraldine; Wilson, Mark",
  "journal": "Demographic Research",
  "journal_slug": "Demographic_Research",
  "year": 2010,
  "doi": "10.4054/demres.2010.23.11",
  "doi_url": "https://doi.org/10.4054/demres.2010.23.11",
  "share_url": "https://huwenbo-lab.github.io/publication/#doi/10.4054%2Fdemres.2010.23.11",
  "api_url": "https://huwenbo-lab.github.io/publication/api/articles/10.4054/demres.2010.23.11.json",
  "lit_db": {
    "overview": "https://raw.githubusercontent.com/huwenbo-lab/publication/main/lit_db/overview.md",
    "journal_titles": "https://raw.githubusercontent.com/huwenbo-lab/publication/main/lit_db/titles/by_journal/Demographic_Research.md",
    "journal_abstracts": "https://raw.githubusercontent.com/huwenbo-lab/publication/main/lit_db/abstracts/2010_2019/Demographic_Research.md"
  },
  "generated_at": "2026-04-11T17:57:23"
}
