{
  "title": "Demography and the social contract",
  "abstract": "Abstract As the most demographically complex nation in the world, the United States faces ever more formidable challenges to fulfill its commitment to the democratic values of equity and inclusion as the foreign-born share of the population increases. Immigration, the major source of the contemporary diversification of the population, provides several lessons about how to prepare for that future within a framework of social justice and how to realign recent demographic trends with cherished democratic principles. A review of historical and contemporary controversies about the representation of the foreign-born and alien suffrage both illustrates the reemergence of ascriptive civic hierarchies and highlights some potentially deleterious social and civic consequences of recent demographic trends.",
  "authors": [
    {
      "raw": "Tienda, Marta",
      "family": "Tienda",
      "given": "Marta"
    }
  ],
  "authors_text": "Tienda, Marta",
  "journal": "Demography",
  "journal_slug": "Demography",
  "year": 2002,
  "doi": "10.1353/dem.2002.0041",
  "doi_url": "https://doi.org/10.1353/dem.2002.0041",
  "share_url": "https://huwenbo-lab.github.io/publication/#doi/10.1353%2Fdem.2002.0041",
  "api_url": "https://huwenbo-lab.github.io/publication/api/articles/10.1353/dem.2002.0041.json",
  "lit_db": {
    "overview": "https://raw.githubusercontent.com/huwenbo-lab/publication/main/lit_db/overview.md",
    "journal_titles": "https://raw.githubusercontent.com/huwenbo-lab/publication/main/lit_db/titles/by_journal/Demography.md",
    "journal_abstracts": "https://raw.githubusercontent.com/huwenbo-lab/publication/main/lit_db/abstracts/2000_2009/Demography.md"
  }
}
