{
  "title": "TRENDS IN DELAYED AND NON-MARRIAGE IN PENINSULAR MALAYSIA",
  "abstract": "The marriage pattern in Malaysia has changed dramatically since the 1940s. The general trend is one of increasing age at marriage and non-marriage. Between 1970 and 2000, the singulate mean age at marriage among men and women increased about three years each, from 25.5 years and 22.0 years to 28.8 years and 25.3 years, respectively. During the same period, the proportion of never married among those aged 30–34 doubled from 12 per cent to 25 per cent among males and from 6 per cent to 12 per cent among females. This paper uses data from population censuses to examine the trends and correlates of delayed marriage for the three main ethnic groups in Peninsular Malaysia. Data from sample surveys are also used to shed some light on contemporary marriage behaviour. Malaysia has made great strides in socio-economic development that benefited all segments of society. However, the effects of socio-economic development on marriage postponement and non-marriage have been stronger for non-Malays than for Malays. This can probably be explained by socio-cultural and religious practices.",
  "authors": [
    {
      "raw": "Nai Peng, Tey",
      "family": "Nai Peng",
      "given": "Tey"
    }
  ],
  "authors_text": "Nai Peng, Tey",
  "journal": "Asian Population Studies",
  "journal_slug": "Asian_Population_Studies",
  "year": 2007,
  "doi": "10.1080/17441730701746391",
  "doi_url": "https://doi.org/10.1080/17441730701746391",
  "share_url": "https://huwenbo-lab.github.io/publication/#doi/10.1080%2F17441730701746391",
  "api_url": "https://huwenbo-lab.github.io/publication/api/articles/10.1080/17441730701746391.json",
  "lit_db": {
    "overview": "https://raw.githubusercontent.com/huwenbo-lab/publication/main/lit_db/overview.md",
    "journal_titles": "https://raw.githubusercontent.com/huwenbo-lab/publication/main/lit_db/titles/by_journal/Asian_Population_Studies.md",
    "journal_abstracts": "https://raw.githubusercontent.com/huwenbo-lab/publication/main/lit_db/abstracts/2000_2009/Asian_Population_Studies.md"
  }
}
