{
  "title": "Fiscal Impoverishment in Rich Democracies",
  "abstract": "This article introduces fiscal impoverishment as a framework for comparative poverty research. We invert standard analyses of welfare state policy and household poverty by focusing not on poverty alleviation but poverty creation and exacerbation. Using harmonized household survey data, we show how the income and payroll taxes most rich countries rely on to finance the public sector serve to push households (further) into poverty. We estimate that across rich democracies on average about one in four households in poverty are made poorer on net after taxes and transfers; with fiscal impoverishment levels ranging from <10% in some countries to more than 70% in others, revealing extreme cross-national variation in how the pocketbooks of poor households are impacted by national tax and transfer policy. We go on to show that fiscal impoverishment does not track with standard measures of welfare state generosity but is instead largely determined by design of income tax systems, particularly a country's relative reliance on (regressive) payroll taxes versus (progressive) income taxes. We consider the implications of fiscal impoverishment for assessing welfare state performance and for comparative poverty research.",
  "authors": [
    {
      "raw": "Schechtl, Manuel",
      "family": "Schechtl",
      "given": "Manuel"
    },
    {
      "raw": "O'Brien, Rourke L.",
      "family": "O'Brien",
      "given": "Rourke L."
    }
  ],
  "authors_text": "Schechtl, Manuel; O'Brien, Rourke L.",
  "journal": "Social Forces",
  "journal_slug": "Social_Forces",
  "year": 2024,
  "doi": "10.1093/sf/soad133",
  "doi_url": "https://doi.org/10.1093/sf/soad133",
  "share_url": "https://huwenbo-lab.github.io/publication/#doi/10.1093%2Fsf%2Fsoad133",
  "api_url": "https://huwenbo-lab.github.io/publication/api/articles/10.1093/sf/soad133.json",
  "lit_db": {
    "overview": "https://raw.githubusercontent.com/huwenbo-lab/publication/main/lit_db/overview.md",
    "journal_titles": "https://raw.githubusercontent.com/huwenbo-lab/publication/main/lit_db/titles/by_journal/Social_Forces.md",
    "journal_abstracts": "https://raw.githubusercontent.com/huwenbo-lab/publication/main/lit_db/abstracts/2020_2026/Social_Forces.md"
  }
}
