{
  "title": "Port of Call: How Ships Shape Foreign-Local Encounters",
  "abstract": "The study of foreign-local encounters is at the heart of much of social scientific research, from the dynamics of globalized travel and migration to the study of colonialism and places of foreign control. These interactions are often both shaped by structural inequalities and fleeting. How do organizations shape these interactions? This question of how organizations interact with their environment is a central puzzle that motivates the field of organizational studies. Yet most research assumes that organizations are, or intend to be, permanent. What about transient organizations, those that neither have nor intend to have a permanent presence? How do these types of organizations shape foreign-local interactions? Using qualitative interviews, documents, and ethnographic observations, I argue that Goffman's work on total institutions is useful for understanding this question in cases where transient organizations are self-sustaining. Examining a US military ship and an evangelical missionary ship docked at the Subic Bay Freeport Zone, Philippines, I show how a ship's total institutional form and logics shape-or affect-foreign-local encounters in three ways, by: (1) gendering the geography of the host community, (2) perpetuating stereotypes, and (3) influencing local markets. By shifting scholarly focus from the dynamics of permanent organizations to the intended and unintended consequences of transient total institutions, I reveal how transient actors can have profound effects on social life. Given the proliferation of ships around the world, my findings have broader implications beyond the two I study.",
  "authors": [
    {
      "raw": "Reyes, Victoria",
      "family": "Reyes",
      "given": "Victoria"
    }
  ],
  "authors_text": "Reyes, Victoria",
  "journal": "Social Forces",
  "journal_slug": "Social_Forces",
  "year": 2018,
  "doi": "10.1093/sf/sox074",
  "doi_url": "https://doi.org/10.1093/sf/sox074",
  "share_url": "https://huwenbo-lab.github.io/publication/#doi/10.1093%2Fsf%2Fsox074",
  "api_url": "https://huwenbo-lab.github.io/publication/api/articles/10.1093/sf/sox074.json",
  "lit_db": {
    "overview": "https://raw.githubusercontent.com/huwenbo-lab/publication/main/lit_db/overview.md",
    "journal_titles": "https://raw.githubusercontent.com/huwenbo-lab/publication/main/lit_db/titles/by_journal/Social_Forces.md",
    "journal_abstracts": "https://raw.githubusercontent.com/huwenbo-lab/publication/main/lit_db/abstracts/2010_2019/Social_Forces.md"
  }
}
