{
  "title": "Leveling the playing field? Students' educational attainment and states' performance testing",
  "abstract": "Sociologists and policy makers have hotly debated whether American public schools reflect the common school ideal, in which all students have access to similar opportunities for learning, and how reform may better approximate that ideal. In the analyses reported here, the authors explore variations among states in the relationships of students' educational attainment with their family backgrounds, eighth-grade course placements, and high school teachers' assessments of their academic potential. The focus is on whether states' mandatory testing policies are associated with differences in public school students' attainment, measured by the likelihood of obtaining a high school diploma and the amount of advanced mathematics course credits students earn. The findings indicate that eighth-grade mathematics courses and teachers' expectations have a weaker relationship with these student outcomes in states with more extensive academic testing and that socioeconomic status has a stronger relationship with these outcomes in states that link test performance to consequences for schools. The results also suggest that outcomes are likely to vary significantly among states for academically vulnerable students.",
  "authors": [
    {
      "raw": "Muller, C",
      "family": "Muller",
      "given": "C"
    },
    {
      "raw": "Schiller, KS",
      "family": "Schiller",
      "given": "KS"
    }
  ],
  "authors_text": "Muller, C; Schiller, KS",
  "journal": "Sociology of Education",
  "journal_slug": "Sociology_of_Education",
  "year": 2000,
  "doi": "10.2307/2673216",
  "doi_url": "https://doi.org/10.2307/2673216",
  "share_url": "https://huwenbo-lab.github.io/publication/#doi/10.2307%2F2673216",
  "api_url": "https://huwenbo-lab.github.io/publication/api/articles/10.2307/2673216.json",
  "lit_db": {
    "overview": "https://raw.githubusercontent.com/huwenbo-lab/publication/main/lit_db/overview.md",
    "journal_titles": "https://raw.githubusercontent.com/huwenbo-lab/publication/main/lit_db/titles/by_journal/Sociology_of_Education.md",
    "journal_abstracts": "https://raw.githubusercontent.com/huwenbo-lab/publication/main/lit_db/abstracts/2000_2009/Sociology_of_Education.md"
  },
  "generated_at": "2026-04-11T17:57:33"
}
