{
  "title": "The international women's movement and women's political representation, 1893-2003",
  "abstract": "Women political representation, once considered unacceptable by politicians and their publics, is now actively encouraged by powerful international actors. In this article, the authors ask how the growth and discourse of the international women movement affected women acquisition of political power over time. To answer this question, they use event history techniques to address women political representation in more than 150 countries over 110 years (1893-2003). They consider multiple political outcomes: female suffrage, first female parliamentarian, and achievement of 10, 20, and 30 percent women in a country national legislature. The findings show that increasing global pressurefor the inclusion of women in international politics and the changing discourse of the international women movement help to explain women acquisition of these multiple political outcomes. Furthermore, by adding these concepts to traditional domestic models of women in politics, the authors demonstrate that country-level political, social structural, and cultural characteristics cause countries to act in conjunction with, or in opposition to, these global pressures. This is thefirst time that research on women in politics has considered such a comprehensive list of countries, time points, and outcomes.",
  "authors": [
    {
      "raw": "Paxton, Pamela",
      "family": "Paxton",
      "given": "Pamela"
    },
    {
      "raw": "Hughes, Melanie M.",
      "family": "Hughes",
      "given": "Melanie M."
    },
    {
      "raw": "Green, Jennifer L.",
      "family": "Green",
      "given": "Jennifer L."
    }
  ],
  "authors_text": "Paxton, Pamela; Hughes, Melanie M.; Green, Jennifer L.",
  "journal": "American Sociological Review",
  "journal_slug": "American_Sociological_Review",
  "year": 2006,
  "doi": "10.1177/000312240607100602",
  "doi_url": "https://doi.org/10.1177/000312240607100602",
  "share_url": "https://huwenbo-lab.github.io/publication/#doi/10.1177%2F000312240607100602",
  "api_url": "https://huwenbo-lab.github.io/publication/api/articles/10.1177/000312240607100602.json",
  "lit_db": {
    "overview": "https://raw.githubusercontent.com/huwenbo-lab/publication/main/lit_db/overview.md",
    "journal_titles": "https://raw.githubusercontent.com/huwenbo-lab/publication/main/lit_db/titles/by_journal/American_Sociological_Review.md",
    "journal_abstracts": "https://raw.githubusercontent.com/huwenbo-lab/publication/main/lit_db/abstracts/2000_2009/American_Sociological_Review.md"
  }
}
