{
  "title": "Bringing Intergenerational Social Mobility Research into the Twenty-first Century: Why Mothers Matter",
  "abstract": "Conventional social mobility research, which measures family social class background relative to only fathers' characteristics, presents an outmoded picture of families-a picture wherein mothers' economic participation is neither common nor important. This article demonstrates that such measurement is theoretically and empirically untenable. Models that incorporate both mothers' and fathers' characteristics into class origin measures fit observed mobility patterns better than do conventional models, and for both men and women. Furthermore, in contrast to the current consensus that conventional measurement strategies do not alter substantive research conclusions, analyses of cohort change in social mobility illustrate the distortions that conventional practice can produce in stratification research findings. By failing to measure the impact of mothers' class, the current practice misses a recent upturn in the importance of family background for class outcomes among men in the United States. The conventional approach suggests no change between cohorts, but updated analyses reveal that inequality of opportunity increased significantly for men born since the mid-1960s compared with those born earlier in the century.",
  "authors": [
    {
      "raw": "Beller, Emily",
      "family": "Beller",
      "given": "Emily"
    }
  ],
  "authors_text": "Beller, Emily",
  "journal": "American Sociological Review",
  "journal_slug": "American_Sociological_Review",
  "year": 2009,
  "doi": "10.1177/000312240907400401",
  "doi_url": "https://doi.org/10.1177/000312240907400401",
  "share_url": "https://huwenbo-lab.github.io/publication/#doi/10.1177%2F000312240907400401",
  "api_url": "https://huwenbo-lab.github.io/publication/api/articles/10.1177/000312240907400401.json",
  "lit_db": {
    "overview": "https://raw.githubusercontent.com/huwenbo-lab/publication/main/lit_db/overview.md",
    "journal_titles": "https://raw.githubusercontent.com/huwenbo-lab/publication/main/lit_db/titles/by_journal/American_Sociological_Review.md",
    "journal_abstracts": "https://raw.githubusercontent.com/huwenbo-lab/publication/main/lit_db/abstracts/2000_2009/American_Sociological_Review.md"
  }
}
