{
  "title": "The Emotional Impact of Unfulfilled Career Aspirations for Stay-at-Home Mothers in Australia",
  "abstract": "Australia has a relatively high proportion of stay-at-home mothers, despite most young women aspiring to combine motherhood with paid work. Using two waves of quantitative data from the 1973-1978 cohort of the Australian Longitudinal Study on Women's Health, and interviews with a subsample of stay-at-home mothers, we aimed to understand the role of agency in women's work-family outcomes and the impact upon their well-being. More than four out of five stay-at-home mothers (83%) had previously aspired to combine motherhood with paid work. There were no differences in mental health scores of stay-at-home mothers according to prior work aspirations. However, stay-at-home mothers had marginally lower life satisfaction, and were more dissatisfied with the progress of their career when they had previously aspired to paid work, compared with unpaid work. Although women described their current situation as a 'choice', their choices were deeply embedded within gendered, social and economic contexts.",
  "authors": [
    {
      "raw": "Johnstone, Melissa",
      "family": "Johnstone",
      "given": "Melissa"
    },
    {
      "raw": "Lucke, Jayne",
      "family": "Lucke",
      "given": "Jayne"
    }
  ],
  "authors_text": "Johnstone, Melissa; Lucke, Jayne",
  "journal": "Journal of Family Issues",
  "journal_slug": "Journal_of_Family_Issues",
  "year": 2022,
  "doi": "10.1177/0192513x211030730",
  "doi_url": "https://doi.org/10.1177/0192513x211030730",
  "share_url": "https://huwenbo-lab.github.io/publication/#doi/10.1177%2F0192513x211030730",
  "api_url": "https://huwenbo-lab.github.io/publication/api/articles/10.1177/0192513x211030730.json",
  "lit_db": {
    "overview": "https://raw.githubusercontent.com/huwenbo-lab/publication/main/lit_db/overview.md",
    "journal_titles": "https://raw.githubusercontent.com/huwenbo-lab/publication/main/lit_db/titles/by_journal/Journal_of_Family_Issues.md",
    "journal_abstracts": "https://raw.githubusercontent.com/huwenbo-lab/publication/main/lit_db/abstracts/2020_2026/Journal_of_Family_Issues.md"
  },
  "generated_at": "2026-04-11T17:57:27"
}
