{
  "title": "Alexithymia, Fear of Intimacy, and Relationship Satisfaction",
  "abstract": "Alexithymia, fear of intimacy, attachment security, and mood variables were examined as predictors of satisfaction in couple relationships after accounting for age, sex, relationship length, and marital status. Participants were 158 adults (52% women and 48% men) in an ongoing couple relationship for 1-19 years. They completed validated measures of the variables of interest online. Bivariate correlations were significant for all predicted associations. Multiple mediation modelling examined the hypothesis that the low relationship satisfaction reported by those with alexithymia can be explained by fear of intimacy, insecure attachment, and negative affect, after accounting for relevant covariates. Mediation was indicated for fear of intimacy and negative affect. Such factors may merit particular attention by clinicians working with alexithymic clients in couples therapy.",
  "authors": [
    {
      "raw": "Lyvers, Michael",
      "family": "Lyvers",
      "given": "Michael"
    },
    {
      "raw": "Pickett, Louisa",
      "family": "Pickett",
      "given": "Louisa"
    },
    {
      "raw": "Needham, Katarina",
      "family": "Needham",
      "given": "Katarina"
    },
    {
      "raw": "Thorberg, Fred Arne",
      "family": "Thorberg",
      "given": "Fred Arne"
    }
  ],
  "authors_text": "Lyvers, Michael; Pickett, Louisa; Needham, Katarina; Thorberg, Fred Arne",
  "journal": "Journal of Family Issues",
  "journal_slug": "Journal_of_Family_Issues",
  "year": 2022,
  "doi": "10.1177/0192513x211010206",
  "doi_url": "https://doi.org/10.1177/0192513x211010206",
  "share_url": "https://huwenbo-lab.github.io/publication/#doi/10.1177%2F0192513x211010206",
  "api_url": "https://huwenbo-lab.github.io/publication/api/articles/10.1177/0192513x211010206.json",
  "lit_db": {
    "overview": "https://raw.githubusercontent.com/huwenbo-lab/publication/main/lit_db/overview.md",
    "journal_titles": "https://raw.githubusercontent.com/huwenbo-lab/publication/main/lit_db/titles/by_journal/Journal_of_Family_Issues.md",
    "journal_abstracts": "https://raw.githubusercontent.com/huwenbo-lab/publication/main/lit_db/abstracts/2020_2026/Journal_of_Family_Issues.md"
  },
  "generated_at": "2026-04-11T17:57:27"
}
