{
  "title": "GENDERING VIOLENCE",
  "abstract": "This article examines the construction of gender within men's accounts of domestic violence. Analyses of in-depth interviews conducted with 33 domestically violent heterosexual men indicate that these batterers used diverse strategies to present themselves as nonviolent, capable, and rational men. Respondents performed gender by contrasting effectual male violence with ineffectual female violence, by claiming that female partners were responsible for the violence in their relationships and by constructing men as victims of a biased criminal justice system. This study suggests that violence against female partners is a means by which batterers reproduce a binary framework of gender.",
  "authors": [
    {
      "raw": "ANDERSON, KRISTIN L.",
      "family": "ANDERSON",
      "given": "KRISTIN L."
    },
    {
      "raw": "UMBERSON, DEBRA",
      "family": "UMBERSON",
      "given": "DEBRA"
    }
  ],
  "authors_text": "ANDERSON, KRISTIN L.; UMBERSON, DEBRA",
  "journal": "Gender & Society",
  "journal_slug": "Gender_and_Society",
  "year": 2001,
  "doi": "10.1177/089124301015003003",
  "doi_url": "https://doi.org/10.1177/089124301015003003",
  "share_url": "https://huwenbo-lab.github.io/publication/#doi/10.1177%2F089124301015003003",
  "api_url": "https://huwenbo-lab.github.io/publication/api/articles/10.1177/089124301015003003.json",
  "lit_db": {
    "overview": "https://raw.githubusercontent.com/huwenbo-lab/publication/main/lit_db/overview.md",
    "journal_titles": "https://raw.githubusercontent.com/huwenbo-lab/publication/main/lit_db/titles/by_journal/Gender_and_Society.md",
    "journal_abstracts": "https://raw.githubusercontent.com/huwenbo-lab/publication/main/lit_db/abstracts/2000_2009/Gender_and_Society.md"
  },
  "generated_at": "2026-04-11T17:57:25"
}
