{
  "title": "Disconnecting Labour? The Labour Process in the UK Fast Fashion Value Chain",
  "abstract": "This article focuses on the interlinkages between the labour process and global value chains. It draws on the renewed growth in UK apparel manufacturing, specifically within the fast fashion value chain, and asks how value chain requirements are translated into the labour process as well as how the latter enables quick response manufacturing. The case study shows how buyer-lead firms engender accelerated capital circuits of fast fashion which rely on an increased segmentation of manufacturers and workers, the elimination of unproductive spaces in the labour process, and a further rise in the informalisation and precarity of labour. The article demonstrates a strategic disconnection within the fast fashion value chain: upstream manufacturers are only able to satisfy lead firms’ economic and operational standards if they disconnect – informalise – labour from the latter’s ‘ethical’ standards.",
  "authors": [
    {
      "raw": "Hammer, Nikolaus",
      "family": "Hammer",
      "given": "Nikolaus"
    },
    {
      "raw": "Plugor, Réka",
      "family": "Plugor",
      "given": "Réka"
    }
  ],
  "authors_text": "Hammer, Nikolaus; Plugor, Réka",
  "journal": "Work, Employment and Society",
  "journal_slug": "Work_Employment_and_Society",
  "year": 2019,
  "doi": "10.1177/0950017019847942",
  "doi_url": "https://doi.org/10.1177/0950017019847942",
  "share_url": "https://huwenbo-lab.github.io/publication/#doi/10.1177%2F0950017019847942",
  "api_url": "https://huwenbo-lab.github.io/publication/api/articles/10.1177/0950017019847942.json",
  "lit_db": {
    "overview": "https://raw.githubusercontent.com/huwenbo-lab/publication/main/lit_db/overview.md",
    "journal_titles": "https://raw.githubusercontent.com/huwenbo-lab/publication/main/lit_db/titles/by_journal/Work_Employment_and_Society.md",
    "journal_abstracts": "https://raw.githubusercontent.com/huwenbo-lab/publication/main/lit_db/abstracts/2010_2019/Work_Employment_and_Society.md"
  }
}
