{
  "title": "Upgrading China through Automation: Manufacturers, Workers and the Techno-Developmental State",
  "abstract": "This article analyses how local states, electronics manufacturers and low-skilled workers perceive and make decisions about automation under China’s techno-developmentalism. Since the early 2010s, local states have made automation – specifically, the substitution of robots for human workers – the linchpin of their techno-developmentalist strategy and set statistical targets to facilitate policy implementation. Although manufacturers realised the limitations of such substitution, most continue to overstate the power of robots in order to receive material and symbolic benefits from local states, which rely on manufacturers to achieve their statistical targets. Meanwhile, most low-skilled workers embrace the state’s vision and see automation as beneficial for national progress, although these workers are the most excluded by state policy. Essentially, China’s techno-developmentalism has led to symbiotic state-capital relations that marginalise low-skilled workers, while reproducing a national sociotechnical imaginary that prioritises abstract notions of technological progress over the actual efficacy of automation, labour protection and social equality.",
  "authors": [
    {
      "raw": "Lei, Ya-Wen",
      "family": "Lei",
      "given": "Ya-Wen"
    }
  ],
  "authors_text": "Lei, Ya-Wen",
  "journal": "Work, Employment and Society",
  "journal_slug": "Work_Employment_and_Society",
  "year": 2021,
  "doi": "10.1177/0950017021999198",
  "doi_url": "https://doi.org/10.1177/0950017021999198",
  "share_url": "https://huwenbo-lab.github.io/publication/#doi/10.1177%2F0950017021999198",
  "api_url": "https://huwenbo-lab.github.io/publication/api/articles/10.1177/0950017021999198.json",
  "lit_db": {
    "overview": "https://raw.githubusercontent.com/huwenbo-lab/publication/main/lit_db/overview.md",
    "journal_titles": "https://raw.githubusercontent.com/huwenbo-lab/publication/main/lit_db/titles/by_journal/Work_Employment_and_Society.md",
    "journal_abstracts": "https://raw.githubusercontent.com/huwenbo-lab/publication/main/lit_db/abstracts/2020_2026/Work_Employment_and_Society.md"
  }
}
