{
  "title": "Sociology’s Role in Responding to Inequality: Introduction to the Special Collection",
  "abstract": "Inequality has long been a central focus of sociological research, but some argue that sociology as a discipline has actually done little to reduce inequality in society. This special collection asks whether sociology, and the social sciences generally, have more to offer. Two main articles make the case, the first by exploring the potential of sociology to move from framing inequality to examining responses to inequality and the second by laying out six pathways through which social science research can contribute to inequality reduction. These articles will be followed by a series of commentaries.",
  "authors": [
    {
      "raw": "Gamoran, Adam",
      "family": "Gamoran",
      "given": "Adam"
    }
  ],
  "authors_text": "Gamoran, Adam",
  "journal": "Socius",
  "journal_slug": "Socius",
  "year": 2021,
  "doi": "10.1177/23780231211020201",
  "doi_url": "https://doi.org/10.1177/23780231211020201",
  "share_url": "https://huwenbo-lab.github.io/publication/#doi/10.1177%2F23780231211020201",
  "api_url": "https://huwenbo-lab.github.io/publication/api/articles/10.1177/23780231211020201.json",
  "lit_db": {
    "overview": "https://raw.githubusercontent.com/huwenbo-lab/publication/main/lit_db/overview.md",
    "journal_titles": "https://raw.githubusercontent.com/huwenbo-lab/publication/main/lit_db/titles/by_journal/Socius.md",
    "journal_abstracts": "https://raw.githubusercontent.com/huwenbo-lab/publication/main/lit_db/abstracts/2020_2026/Socius.md"
  }
}
