{
  "title": "Immigrant Organizations",
  "abstract": "We call for incorporating organizations into migration scholarship, and for considering immigrants in organizational research. By centering immigrant organizations (IOs) as a unit of analysis, migration scholars can reconsider whether and how IOs affect well-being, integration, political voice, identities, globalization, and development. Migration scholars must learn from scholars of organizations, but organization scholars must in turn question assumptions of nativity and citizenship in their research. Doing so illuminates the unique challenges-and, at times, opportunities-faced by IOs, especially regarding inequities tied to legal status and stigmatization. We further argue that cross-national and transnational analyses of IOs help unpack organizational embeddedness-that is, the ways in which contexts at the local, national, binational, and geopolitical levels generate opportunities and constraints. Studying IOs raises critical questions of civic inequality and organizational stigma but also highlights IOs' potential to give voice to and effect positive change for migrant communities.",
  "authors": [
    {
      "raw": "Bloemraad, Irene",
      "family": "Bloemraad",
      "given": "Irene"
    },
    {
      "raw": "Chaudhary, Ali R.",
      "family": "Chaudhary",
      "given": "Ali R."
    },
    {
      "raw": "Gleeson, Shannon",
      "family": "Gleeson",
      "given": "Shannon"
    }
  ],
  "authors_text": "Bloemraad, Irene; Chaudhary, Ali R.; Gleeson, Shannon",
  "journal": "Annual Review of Sociology",
  "journal_slug": "Annual_Review_of_Sociology",
  "year": 2022,
  "doi": "10.1146/annurev-soc-030420-015613",
  "doi_url": "https://doi.org/10.1146/annurev-soc-030420-015613",
  "share_url": "https://huwenbo-lab.github.io/publication/#doi/10.1146%2Fannurev-soc-030420-015613",
  "api_url": "https://huwenbo-lab.github.io/publication/api/articles/10.1146/annurev-soc-030420-015613.json",
  "lit_db": {
    "overview": "https://raw.githubusercontent.com/huwenbo-lab/publication/main/lit_db/overview.md",
    "journal_titles": "https://raw.githubusercontent.com/huwenbo-lab/publication/main/lit_db/titles/by_journal/Annual_Review_of_Sociology.md",
    "journal_abstracts": "https://raw.githubusercontent.com/huwenbo-lab/publication/main/lit_db/abstracts/2020_2026/Annual_Review_of_Sociology.md"
  }
}
